isbnlib_mcues/__init__.py
isbnlib_mcues/_mcues.py
isbnlib_mcues/_mcueswebservice.py
isbnlib_mcues-0.0.3.dist-info/LICENSE-LGPL.txt
isbnlib_mcues-0.0.3.dist-info/METADATA
isbnlib_mcues-0.0.3.dist-info/WHEEL
isbnlib_mcues-0.0.3.dist-info/entry_points.txt
isbnlib_mcues-0.0.3.dist-info/top_level.txt
isbnlib_mcues-0.0.3.dist-info/RECORD
